leetgo_py/__init__.py
leetgo_py/list.py
leetgo_py/parse.py
leetgo_py/tree.py
leetgo_py/utils.py
leetgo_py-0.2.4.dist-info/METADATA
leetgo_py-0.2.4.dist-info/WHEEL
leetgo_py-0.2.4.dist-info/RECORD
